quotefancy/__init__.py
quotefancy-1.0.dist-info/METADATA
quotefancy-1.0.dist-info/WHEEL
quotefancy-1.0.dist-info/top_level.txt
quotefancy-1.0.dist-info/RECORD
