Metadata-Version: 2.1
Name: quotefancy
Version: 1.0
Summary: Get Quotes from QuoteFancy.com
Home-page: UNKNOWN
Author: New-dev0
License: UNKNOWN
Platform: UNKNOWN
Classifier: Programming Language :: Python :: 3
Classifier: License :: OSI Approved :: MIT License
Classifier: Operating System :: OS Independent
Requires-Python: >=3.6
Requires-Dist: bs4
Requires-Dist: requests
